django_light/__init__.py
django_light/static/django_light/django_light.css
django_light/templates/admin/base.html
django_light-0.1.0.post1.dist-info/LICENSE
django_light-0.1.0.post1.dist-info/METADATA
django_light-0.1.0.post1.dist-info/WHEEL
django_light-0.1.0.post1.dist-info/top_level.txt
django_light-0.1.0.post1.dist-info/RECORD
